{
  "users": [
    {
      "id": "d080",
      "fullName": "ماريو فلتس شوقي",
      "age": "34",
      "address": "محمد جاد علي ",
      "phone": "010293333333",
      "email": "mario1234@gmail.com",
      "password": "1234",
      "type": "patient",
      "providerType": "",
      "idCard": {},
      "degree": null,
      "license": null
    },
    {
      "id": "d811",
      "fullName": "Christina Bolis Rezkallh Bolis",
      "age": "13",
      "address": "ىهصقىهصى",
      "phone": "9282094830",
      "email": "mari111@gmail.com",
      "password": "1234",
      "type": "provider",
      "providerType": "nurse",
      "idCard": {},
      "degree": {},
      "license": {}
    }
  ],
  "nurseServices": [
    {
      "id": 1,
      "name": "قياس ضغط الدم",
      "basePrice": 50
    },
    {
      "id": 2,
      "name": "قياس السكر في الدم",
      "basePrice": 60
    },
    {
      "id": 3,
      "name": "حقن عضلي",
      "basePrice": 70
    },
    {
      "id": 4,
      "name": "حقن وريدي",
      "basePrice": 80
    },
    {
      "id": 5,
      "name": "تركيب كانيولا",
      "basePrice": 90
    },
    {
      "id": 6,
      "name": "تغيير ضماد جرح",
      "basePrice": 100
    },
    {
      "id": 7,
      "name": "سحب عينات دم",
      "basePrice": 110
    },
    {
      "id": 8,
      "name": "تركيب قسطرة بولية",
      "basePrice": 120
    },
    {
      "id": 9,
      "name": "رعاية مرضى الفراش",
      "basePrice": 130
    },
    {
      "id": 10,
      "name": "قياس حرارة الجسم",
      "basePrice": 40
    },
    {
      "id": 11,
      "name": "إعطاء أدوية بالفم",
      "basePrice": 50
    },
    {
      "id": 12,
      "name": "مراقبة العلامات الحيوية",
      "basePrice": 60
    },
    {
      "id": 13,
      "name": "تغيير قسطرة بولية",
      "basePrice": 70
    },
    {
      "id": 14,
      "name": "رعاية ما بعد العمليات",
      "basePrice": 150
    },
    {
      "id": 15,
      "name": "تغيير جبيرة",
      "basePrice": 100
    },
    {
      "id": 16,
      "name": "إعطاء محلول وريدي",
      "basePrice": 90
    },
    {
      "id": 17,
      "name": "تغيير أنبوب تغذية",
      "basePrice": 80
    },
    {
      "id": 18,
      "name": "رعاية مرضى السكر",
      "basePrice": 70
    },
    {
      "id": 19,
      "name": "رعاية مرضى الضغط",
      "basePrice": 70
    },
    {
      "id": 20,
      "name": "تغيير شاش وضمادات",
      "basePrice": 60
    },
    {
      "id": 21,
      "name": "إعطاء أدوية بالحقن",
      "basePrice": 80
    },
    {
      "id": 22,
      "name": "رعاية مرضى القلب",
      "basePrice": 120
    },
    {
      "id": 23,
      "name": "رعاية مرضى الكلى",
      "basePrice": 110
    },
    {
      "id": 24,
      "name": "رعاية مرضى السرطان",
      "basePrice": 130
    },
    {
      "id": 25,
      "name": "تغيير قسطرة وريدية",
      "basePrice": 90
    },
    {
      "id": 26,
      "name": "إعطاء أدوية عن طريق الفم",
      "basePrice": 50
    },
    {
      "id": 27,
      "name": "رعاية مرضى الجهاز التنفسي",
      "basePrice": 100
    },
    {
      "id": 28,
      "name": "رعاية مرضى الأطفال",
      "basePrice": 80
    },
    {
      "id": 29,
      "name": "رعاية كبار السن",
      "basePrice": 120
    },
    {
      "id": 30,
      "name": "تغيير أنبوب بولي",
      "basePrice": 70
    },
    {
      "id": 31,
      "name": "تغيير أنبوب أنفي معدي",
      "basePrice": 80
    },
    {
      "id": 32,
      "name": "رعاية مرضى الحروق",
      "basePrice": 140
    },
    {
      "id": 33,
      "name": "رعاية مرضى الجلطات",
      "basePrice": 130
    },
    {
      "id": 34,
      "name": "رعاية مرضى العظام",
      "basePrice": 110
    },
    {
      "id": 35,
      "name": "رعاية مرضى الأعصاب",
      "basePrice": 120
    },
    {
      "id": 36,
      "name": "رعاية مرضى الجهاز الهضمي",
      "basePrice": 100
    },
    {
      "id": 37,
      "name": "رعاية مرضى الجهاز البولي",
      "basePrice": 90
    },
    {
      "id": 38,
      "name": "رعاية مرضى الجهاز التنفسي",
      "basePrice": 100
    },
    {
      "id": 39,
      "name": "رعاية مرضى الأورام",
      "basePrice": 130
    },
    {
      "id": 40,
      "name": "رعاية مرضى الأطفال حديثي الولادة",
      "basePrice": 150
    },
    {
      "id": 41,
      "name": "رعاية مرضى الغيبوبة",
      "basePrice": 140
    },
    {
      "id": 42,
      "name": "رعاية مرضى الصرع",
      "basePrice": 120
    },
    {
      "id": 43,
      "name": "رعاية مرضى التهابات الكبد",
      "basePrice": 110
    },
    {
      "id": 44,
      "name": "رعاية مرضى الفشل الكلوي",
      "basePrice": 130
    },
    {
      "id": 45,
      "name": "رعاية مرضى التهابات الصدر",
      "basePrice": 100
    },
    {
      "id": 46,
      "name": "رعاية مرضى الربو",
      "basePrice": 90
    },
    {
      "id": 47,
      "name": "رعاية مرضى السكري",
      "basePrice": 80
    },
    {
      "id": 48,
      "name": "رعاية مرضى الضغط المرتفع",
      "basePrice": 80
    },
    {
      "id": 49,
      "name": "رعاية مرضى القلب المزمن",
      "basePrice": 120
    },
    {
      "id": 50,
      "name": "رعاية مرضى السرطان المزمن",
      "basePrice": 140
    }
  ],
  "doctorServices": [
    {
      "id": 1,
      "name": "كشف طوارئ منزلي",
      "basePrice": 350
    },
    {
      "id": 2,
      "name": "كشف باطنة منزلي",
      "basePrice": 300
    },
    {
      "id": 3,
      "name": "كشف أطفال منزلي",
      "basePrice": 320
    },
    {
      "id": 4,
      "name": "كشف عظام منزلي",
      "basePrice": 340
    },
    {
      "id": 5,
      "name": "كشف قلب منزلي",
      "basePrice": 400
    },
    {
      "id": 6,
      "name": "كشف جلدية منزلي",
      "basePrice": 280
    },
    {
      "id": 7,
      "name": "كشف أنف وأذن منزلي",
      "basePrice": 270
    },
    {
      "id": 8,
      "name": "كشف رمد منزلي",
      "basePrice": 260
    },
    {
      "id": 9,
      "name": "كشف مخ وأعصاب منزلي",
      "basePrice": 420
    },
    {
      "id": 10,
      "name": "كشف مسالك بولية منزلي",
      "basePrice": 350
    },
    {
      "id": 11,
      "name": "كشف نساء وتوليد منزلي",
      "basePrice": 370
    },
    {
      "id": 12,
      "name": "كشف جراحة عامة منزلي",
      "basePrice": 390
    },
    {
      "id": 13,
      "name": "كشف صدرية منزلي",
      "basePrice": 310
    },
    {
      "id": 14,
      "name": "كشف أورام منزلي",
      "basePrice": 450
    },
    {
      "id": 15,
      "name": "كشف غدد صماء منزلي",
      "basePrice": 330
    },
    {
      "id": 16,
      "name": "كشف كلى منزلي",
      "basePrice": 360
    },
    {
      "id": 17,
      "name": "كشف قلب أطفال منزلي",
      "basePrice": 410
    },
    {
      "id": 18,
      "name": "كشف أمراض دم منزلي",
      "basePrice": 320
    },
    {
      "id": 19,
      "name": "كشف روماتيزم منزلي",
      "basePrice": 340
    },
    {
      "id": 20,
      "name": "كشف أمراض معدة منزلي",
      "basePrice": 300
    },
    {
      "id": 21,
      "name": "كشف أمراض كبد منزلي",
      "basePrice": 350
    },
    {
      "id": 22,
      "name": "كشف أمراض صدر منزلي",
      "basePrice": 310
    },
    {
      "id": 23,
      "name": "كشف أمراض قلب منزلي",
      "basePrice": 400
    },
    {
      "id": 24,
      "name": "كشف أمراض عيون منزلي",
      "basePrice": 260
    },
    {
      "id": 25,
      "name": "كشف أمراض أنف وأذن منزلي",
      "basePrice": 270
    },
    {
      "id": 26,
      "name": "كشف أمراض جلدية منزلي",
      "basePrice": 280
    },
    {
      "id": 27,
      "name": "كشف أمراض مخ وأعصاب منزلي",
      "basePrice": 420
    },
    {
      "id": 28,
      "name": "كشف أمراض عظام منزلي",
      "basePrice": 340
    },
    {
      "id": 29,
      "name": "كشف أمراض نساء منزلي",
      "basePrice": 370
    },
    {
      "id": 30,
      "name": "كشف أمراض أطفال منزلي",
      "basePrice": 320
    },
    {
      "id": 31,
      "name": "كشف أمراض باطنة منزلي",
      "basePrice": 300
    },
    {
      "id": 32,
      "name": "كشف أمراض جراحة عامة منزلي",
      "basePrice": 390
    },
    {
      "id": 33,
      "name": "كشف أمراض كلى منزلي",
      "basePrice": 360
    },
    {
      "id": 34,
      "name": "كشف أمراض غدد صماء منزلي",
      "basePrice": 330
    },
    {
      "id": 35,
      "name": "كشف أمراض دم منزلي",
      "basePrice": 320
    },
    {
      "id": 36,
      "name": "كشف أمراض روماتيزم منزلي",
      "basePrice": 340
    },
    {
      "id": 37,
      "name": "كشف أمراض معدة منزلي",
      "basePrice": 300
    },
    {
      "id": 38,
      "name": "كشف أمراض كبد منزلي",
      "basePrice": 350
    },
    {
      "id": 39,
      "name": "كشف أمراض أورام منزلي",
      "basePrice": 450
    },
    {
      "id": 40,
      "name": "كشف أمراض صدرية منزلي",
      "basePrice": 310
    },
    {
      "id": 41,
      "name": "كشف أمراض قلب أطفال منزلي",
      "basePrice": 410
    },
    {
      "id": 42,
      "name": "كشف أمراض عيون أطفال منزلي",
      "basePrice": 270
    },
    {
      "id": 43,
      "name": "كشف أمراض أنف وأذن أطفال منزلي",
      "basePrice": 280
    },
    {
      "id": 44,
      "name": "كشف أمراض جلدية أطفال منزلي",
      "basePrice": 290
    },
    {
      "id": 45,
      "name": "كشف أمراض مخ وأعصاب أطفال منزلي",
      "basePrice": 430
    },
    {
      "id": 46,
      "name": "كشف أمراض عظام أطفال منزلي",
      "basePrice": 350
    },
    {
      "id": 47,
      "name": "كشف أمراض نساء أطفال منزلي",
      "basePrice": 380
    },
    {
      "id": 48,
      "name": "كشف أمراض باطنة أطفال منزلي",
      "basePrice": 310
    },
    {
      "id": 49,
      "name": "كشف أمراض جراحة عامة أطفال منزلي",
      "basePrice": 400
    },
    {
      "id": 50,
      "name": "كشف أمراض كلى أطفال منزلي",
      "basePrice": 370
    }
  ],
  "physioServices": [
    {
      "id": 1,
      "name": "جلسة علاج طبيعي منزلي",
      "basePrice": 200
    },
    {
      "id": 2,
      "name": "جلسة تأهيل حركي",
      "basePrice": 220
    },
    {
      "id": 3,
      "name": "جلسة علاج طبيعي للأطفال",
      "basePrice": 210
    },
    {
      "id": 4,
      "name": "جلسة علاج طبيعي لكبار السن",
      "basePrice": 230
    },
    {
      "id": 5,
      "name": "جلسة علاج طبيعي للعمود الفقري",
      "basePrice": 250
    },
    {
      "id": 6,
      "name": "جلسة علاج طبيعي للشلل النصفي",
      "basePrice": 260
    },
    {
      "id": 7,
      "name": "جلسة علاج طبيعي للشلل الرباعي",
      "basePrice": 270
    },
    {
      "id": 8,
      "name": "جلسة علاج طبيعي للكسور",
      "basePrice": 240
    },
    {
      "id": 9,
      "name": "جلسة علاج طبيعي للعضلات",
      "basePrice": 220
    },
    {
      "id": 10,
      "name": "جلسة علاج طبيعي للغضاريف",
      "basePrice": 230
    },
    {
      "id": 11,
      "name": "جلسة علاج طبيعي للرقبة",
      "basePrice": 210
    },
    {
      "id": 12,
      "name": "جلسة علاج طبيعي للكتف",
      "basePrice": 220
    },
    {
      "id": 13,
      "name": "جلسة علاج طبيعي للركبة",
      "basePrice": 230
    },
    {
      "id": 14,
      "name": "جلسة علاج طبيعي للكاحل",
      "basePrice": 210
    },
    {
      "id": 15,
      "name": "جلسة علاج طبيعي للقدم",
      "basePrice": 200
    },
    {
      "id": 16,
      "name": "جلسة علاج طبيعي لليد",
      "basePrice": 200
    },
    {
      "id": 17,
      "name": "جلسة علاج طبيعي للأصابع",
      "basePrice": 190
    },
    {
      "id": 18,
      "name": "جلسة علاج طبيعي للظهر",
      "basePrice": 220
    },
    {
      "id": 19,
      "name": "جلسة علاج طبيعي للورك",
      "basePrice": 230
    },
    {
      "id": 20,
      "name": "جلسة علاج طبيعي للحوض",
      "basePrice": 240
    },
    {
      "id": 21,
      "name": "جلسة علاج طبيعي للكتف المتجمد",
      "basePrice": 250
    },
    {
      "id": 22,
      "name": "جلسة علاج طبيعي للانزلاق الغضروفي",
      "basePrice": 260
    },
    {
      "id": 23,
      "name": "جلسة علاج طبيعي للشد العضلي",
      "basePrice": 210
    },
    {
      "id": 24,
      "name": "جلسة علاج طبيعي للتمزق العضلي",
      "basePrice": 220
    },
    {
      "id": 25,
      "name": "جلسة علاج طبيعي للالتواءات",
      "basePrice": 230
    },
    {
      "id": 26,
      "name": "جلسة علاج طبيعي للكسور القديمة",
      "basePrice": 240
    },
    {
      "id": 27,
      "name": "جلسة علاج طبيعي للجلطات",
      "basePrice": 250
    },
    {
      "id": 28,
      "name": "جلسة علاج طبيعي للشلل الدماغي",
      "basePrice": 260
    },
    {
      "id": 29,
      "name": "جلسة علاج طبيعي للضمور العضلي",
      "basePrice": 270
    },
    {
      "id": 30,
      "name": "جلسة علاج طبيعي للضمور العصبي",
      "basePrice": 280
    },
    {
      "id": 31,
      "name": "جلسة علاج طبيعي للكسور الحديثة",
      "basePrice": 240
    },
    {
      "id": 32,
      "name": "جلسة علاج طبيعي للتمزق الأربطة",
      "basePrice": 250
    },
    {
      "id": 33,
      "name": "جلسة علاج طبيعي للشد العصبي",
      "basePrice": 210
    },
    {
      "id": 34,
      "name": "جلسة علاج طبيعي للانزلاق الفقاري",
      "basePrice": 260
    },
    {
      "id": 35,
      "name": "جلسة علاج طبيعي للانزلاق الغضروفي العنقي",
      "basePrice": 270
    },
    {
      "id": 36,
      "name": "جلسة علاج طبيعي للانزلاق الغضروفي القطني",
      "basePrice": 280
    },
    {
      "id": 37,
      "name": "جلسة علاج طبيعي للانزلاق الغضروفي الصدري",
      "basePrice": 290
    },
    {
      "id": 38,
      "name": "جلسة علاج طبيعي للانزلاق الغضروفي العجزي",
      "basePrice": 300
    },
    {
      "id": 39,
      "name": "جلسة علاج طبيعي للانزلاق الغضروفي الحوضي",
      "basePrice": 310
    },
    {
      "id": 40,
      "name": "جلسة علاج طبيعي للانزلاق الغضروفي الوركي",
      "basePrice": 320
    },
    {
      "id": 41,
      "name": "جلسة علاج طبيعي للانزلاق الغضروفي الكتفي",
      "basePrice": 330
    },
    {
      "id": 42,
      "name": "جلسة علاج طبيعي للانزلاق الغضروفي الرسغي",
      "basePrice": 340
    },
    {
      "id": 43,
      "name": "جلسة علاج طبيعي للانزلاق الغضروفي الكاحلي",
      "basePrice": 350
    },
    {
      "id": 44,
      "name": "جلسة علاج طبيعي للانزلاق الغضروفي القدموي",
      "basePrice": 360
    },
    {
      "id": 45,
      "name": "جلسة علاج طبيعي للانزلاق الغضروفي اليدوي",
      "basePrice": 370
    },
    {
      "id": 46,
      "name": "جلسة علاج طبيعي للانزلاق الغضروفي الإصبعي",
      "basePrice": 380
    },
    {
      "id": 47,
      "name": "جلسة علاج طبيعي للانزلاق الغضروفي الرقبي",
      "basePrice": 390
    },
    {
      "id": 48,
      "name": "جلسة علاج طبيعي للانزلاق الغضروفي الكتفي",
      "basePrice": 400
    },
    {
      "id": 49,
      "name": "جلسة علاج طبيعي للانزلاق الغضروفي الحوضي",
      "basePrice": 410
    },
    {
      "id": 50,
      "name": "جلسة علاج طبيعي للانزلاق الغضروفي الوركي",
      "basePrice": 420
    }
  ],
  "pharmacistServices": [
    {
      "id": 1,
      "name": "توصيل دواء منزلي",
      "basePrice": 40
    },
    {
      "id": 2,
      "name": "استشارة دوائية هاتفية",
      "basePrice": 30
    },
    {
      "id": 3,
      "name": "مراجعة روشتة طبية",
      "basePrice": 35
    },
    {
      "id": 4,
      "name": "تجهيز أدوية مزمنة",
      "basePrice": 50
    },
    {
      "id": 5,
      "name": "توصيل مستلزمات طبية",
      "basePrice": 45
    },
    {
      "id": 6,
      "name": "تجهيز أدوية أطفال",
      "basePrice": 40
    },
    {
      "id": 7,
      "name": "تجهيز أدوية كبار السن",
      "basePrice": 45
    },
    {
      "id": 8,
      "name": "توصيل فيتامينات",
      "basePrice": 35
    },
    {
      "id": 9,
      "name": "توصيل أدوية طوارئ",
      "basePrice": 60
    },
    {
      "id": 10,
      "name": "توصيل أدوية أمراض مزمنة",
      "basePrice": 55
    },
    {
      "id": 11,
      "name": "توصيل أدوية أمراض نادرة",
      "basePrice": 70
    },
    {
      "id": 12,
      "name": "توصيل أدوية أطفال",
      "basePrice": 40
    },
    {
      "id": 13,
      "name": "توصيل أدوية نساء وتوليد",
      "basePrice": 50
    },
    {
      "id": 14,
      "name": "توصيل أدوية أمراض قلب",
      "basePrice": 60
    },
    {
      "id": 15,
      "name": "توصيل أدوية أمراض كبد",
      "basePrice": 55
    },
    {
      "id": 16,
      "name": "توصيل أدوية أمراض كلى",
      "basePrice": 55
    },
    {
      "id": 17,
      "name": "توصيل أدوية أمراض صدرية",
      "basePrice": 50
    },
    {
      "id": 18,
      "name": "توصيل أدوية أمراض دم",
      "basePrice": 50
    },
    {
      "id": 19,
      "name": "توصيل أدوية أمراض عيون",
      "basePrice": 45
    },
    {
      "id": 20,
      "name": "توصيل أدوية أمراض جلدية",
      "basePrice": 45
    },
    {
      "id": 21,
      "name": "توصيل أدوية أمراض عظام",
      "basePrice": 50
    },
    {
      "id": 22,
      "name": "توصيل أدوية أمراض مخ وأعصاب",
      "basePrice": 60
    },
    {
      "id": 23,
      "name": "توصيل أدوية أمراض روماتيزم",
      "basePrice": 55
    },
    {
      "id": 24,
      "name": "توصيل أدوية أمراض غدد صماء",
      "basePrice": 50
    },
    {
      "id": 25,
      "name": "توصيل أدوية أمراض معدة",
      "basePrice": 45
    },
    {
      "id": 26,
      "name": "توصيل أدوية أمراض أورام",
      "basePrice": 70
    },
    {
      "id": 27,
      "name": "توصيل أدوية أمراض أطفال",
      "basePrice": 40
    },
    {
      "id": 28,
      "name": "توصيل أدوية أمراض نساء",
      "basePrice": 50
    },
    {
      "id": 29,
      "name": "توصيل أدوية أمراض باطنة",
      "basePrice": 45
    },
    {
      "id": 30,
      "name": "توصيل أدوية أمراض جراحة عامة",
      "basePrice": 55
    },
    {
      "id": 31,
      "name": "توصيل أدوية أمراض كلى أطفال",
      "basePrice": 55
    },
    {
      "id": 32,
      "name": "توصيل أدوية أمراض قلب أطفال",
      "basePrice": 60
    },
    {
      "id": 33,
      "name": "توصيل أدوية أمراض عيون أطفال",
      "basePrice": 45
    },
    {
      "id": 34,
      "name": "توصيل أدوية أمراض جلدية أطفال",
      "basePrice": 45
    },
    {
      "id": 35,
      "name": "توصيل أدوية أمراض عظام أطفال",
      "basePrice": 50
    },
    {
      "id": 36,
      "name": "توصيل أدوية أمراض مخ وأعصاب أطفال",
      "basePrice": 60
    },
    {
      "id": 37,
      "name": "توصيل أدوية أمراض روماتيزم أطفال",
      "basePrice": 55
    },
    {
      "id": 38,
      "name": "توصيل أدوية أمراض غدد صماء أطفال",
      "basePrice": 50
    },
    {
      "id": 39,
      "name": "توصيل أدوية أمراض معدة أطفال",
      "basePrice": 45
    },
    {
      "id": 40,
      "name": "توصيل أدوية أمراض أورام أطفال",
      "basePrice": 70
    },
    {
      "id": 41,
      "name": "توصيل أدوية أمراض صدرية أطفال",
      "basePrice": 50
    },
    {
      "id": 42,
      "name": "توصيل أدوية أمراض دم أطفال",
      "basePrice": 50
    },
    {
      "id": 43,
      "name": "توصيل أدوية أمراض نساء أطفال",
      "basePrice": 50
    },
    {
      "id": 44,
      "name": "توصيل أدوية أمراض باطنة أطفال",
      "basePrice": 45
    },
    {
      "id": 45,
      "name": "توصيل أدوية أمراض جراحة عامة أطفال",
      "basePrice": 55
    },
    {
      "id": 46,
      "name": "توصيل أدوية أمراض كبد أطفال",
      "basePrice": 55
    },
    {
      "id": 47,
      "name": "توصيل أدوية أمراض كلى مزمنة",
      "basePrice": 60
    },
    {
      "id": 48,
      "name": "توصيل أدوية أمراض قلب مزمنة",
      "basePrice": 65
    },
    {
      "id": 49,
      "name": "توصيل أدوية أمراض أورام مزمنة",
      "basePrice": 75
    },
    {
      "id": 50,
      "name": "توصيل أدوية أمراض مزمنة أخرى",
      "basePrice": 60
    }
  ],
  "labServices": [
    {
      "id": 1,
      "name": "تحليل دم شامل",
      "basePrice": 80
    },
    {
      "id": 2,
      "name": "تحليل سكر صائم",
      "basePrice": 60
    },
    {
      "id": 3,
      "name": "تحليل سكر فاطر",
      "basePrice": 60
    },
    {
      "id": 4,
      "name": "تحليل وظائف كبد",
      "basePrice": 90
    },
    {
      "id": 5,
      "name": "تحليل وظائف كلى",
      "basePrice": 90
    },
    {
      "id": 6,
      "name": "تحليل بول كامل",
      "basePrice": 50
    },
    {
      "id": 7,
      "name": "تحليل براز كامل",
      "basePrice": 50
    },
    {
      "id": 8,
      "name": "تحليل صورة دم",
      "basePrice": 70
    },
    {
      "id": 9,
      "name": "تحليل هرمونات الغدة الدرقية",
      "basePrice": 120
    },
    {
      "id": 10,
      "name": "تحليل هرمونات الحمل",
      "basePrice": 100
    },
    {
      "id": 11,
      "name": "تحليل فيروسات كبدية",
      "basePrice": 130
    },
    {
      "id": 12,
      "name": "تحليل دهون الدم",
      "basePrice": 90
    },
    {
      "id": 13,
      "name": "تحليل كالسيوم",
      "basePrice": 60
    },
    {
      "id": 14,
      "name": "تحليل فيتامين د",
      "basePrice": 110
    },
    {
      "id": 15,
      "name": "تحليل حديد",
      "basePrice": 70
    },
    {
      "id": 16,
      "name": "تحليل زنك",
      "basePrice": 70
    },
    {
      "id": 17,
      "name": "تحليل نحاس",
      "basePrice": 70
    },
    {
      "id": 18,
      "name": "تحليل مغنيسيوم",
      "basePrice": 70
    },
    {
      "id": 19,
      "name": "تحليل فيتامين ب12",
      "basePrice": 100
    },
    {
      "id": 20,
      "name": "تحليل هيموجلوبين",
      "basePrice": 80
    },
    {
      "id": 21,
      "name": "تحليل سرعة ترسيب",
      "basePrice": 60
    },
    {
      "id": 22,
      "name": "تحليل سكر تراكمي",
      "basePrice": 90
    },
    {
      "id": 23,
      "name": "تحليل بروتينات الدم",
      "basePrice": 80
    },
    {
      "id": 24,
      "name": "تحليل أملاح الدم",
      "basePrice": 80
    },
    {
      "id": 25,
      "name": "تحليل غدة جار درقية",
      "basePrice": 120
    },
    {
      "id": 26,
      "name": "تحليل هرمونات تناسلية",
      "basePrice": 130
    },
    {
      "id": 27,
      "name": "تحليل هرمونات نمو",
      "basePrice": 120
    },
    {
      "id": 28,
      "name": "تحليل هرمونات لبن",
      "basePrice": 110
    },
    {
      "id": 29,
      "name": "تحليل هرمونات أنثوية",
      "basePrice": 120
    },
    {
      "id": 30,
      "name": "تحليل هرمونات ذكرية",
      "basePrice": 120
    },
    {
      "id": 31,
      "name": "تحليل فيروسات الإيدز",
      "basePrice": 150
    },
    {
      "id": 32,
      "name": "تحليل فيروسات الحصبة",
      "basePrice": 130
    },
    {
      "id": 33,
      "name": "تحليل فيروسات الحصبة الألمانية",
      "basePrice": 130
    },
    {
      "id": 34,
      "name": "تحليل فيروسات النكاف",
      "basePrice": 130
    },
    {
      "id": 35,
      "name": "تحليل فيروسات الجدري",
      "basePrice": 130
    },
    {
      "id": 36,
      "name": "تحليل فيروسات الأنفلونزا",
      "basePrice": 130
    },
    {
      "id": 37,
      "name": "تحليل فيروسات كورونا",
      "basePrice": 150
    },
    {
      "id": 38,
      "name": "تحليل فيروسات التهاب الكبد الوبائي",
      "basePrice": 150
    },
    {
      "id": 39,
      "name": "تحليل فيروسات الحمى الشوكية",
      "basePrice": 150
    },
    {
      "id": 40,
      "name": "تحليل فيروسات الحمى المالطية",
      "basePrice": 150
    },
    {
      "id": 41,
      "name": "تحليل فيروسات الحمى الصفراء",
      "basePrice": 150
    },
    {
      "id": 42,
      "name": "تحليل فيروسات الحمى النزفية",
      "basePrice": 150
    },
    {
      "id": 43,
      "name": "تحليل فيروسات الحمى القرمزية",
      "basePrice": 150
    },
    {
      "id": 44,
      "name": "تحليل فيروسات الحمى الوردية",
      "basePrice": 150
    },
    {
      "id": 45,
      "name": "تحليل فيروسات الحمى الزرقاء",
      "basePrice": 150
    },
    {
      "id": 46,
      "name": "تحليل فيروسات الحمى السوداء",
      "basePrice": 150
    },
    {
      "id": 47,
      "name": "تحليل فيروسات الحمى البيضاء",
      "basePrice": 150
    },
    {
      "id": 48,
      "name": "تحليل فيروسات الحمى الخضراء",
      "basePrice": 150
    },
    {
      "id": 49,
      "name": "تحليل فيروسات الحمى البنفسجية",
      "basePrice": 150
    },
    {
      "id": 50,
      "name": "تحليل فيروسات الحمى البرتقالية",
      "basePrice": 150
    }
  ],
  "xrayServices": [
    {
      "id": 1,
      "name": "أشعة سينية للصدر",
      "basePrice": 120
    },
    {
      "id": 2,
      "name": "أشعة سينية للبطن",
      "basePrice": 130
    },
    {
      "id": 3,
      "name": "أشعة سينية للحوض",
      "basePrice": 140
    },
    {
      "id": 4,
      "name": "أشعة سينية للعمود الفقري",
      "basePrice": 150
    },
    {
      "id": 5,
      "name": "أشعة سينية للرأس",
      "basePrice": 120
    },
    {
      "id": 6,
      "name": "أشعة سينية للذراع",
      "basePrice": 110
    },
    {
      "id": 7,
      "name": "أشعة سينية للساق",
      "basePrice": 110
    },
    {
      "id": 8,
      "name": "أشعة سينية للقدم",
      "basePrice": 110
    },
    {
      "id": 9,
      "name": "أشعة سينية لليد",
      "basePrice": 110
    },
    {
      "id": 10,
      "name": "أشعة سينية للكتف",
      "basePrice": 120
    },
    {
      "id": 11,
      "name": "أشعة سينية للركبة",
      "basePrice": 120
    },
    {
      "id": 12,
      "name": "أشعة سينية للكاحل",
      "basePrice": 120
    },
    {
      "id": 13,
      "name": "أشعة سينية للفخذ",
      "basePrice": 130
    },
    {
      "id": 14,
      "name": "أشعة سينية للرسغ",
      "basePrice": 120
    },
    {
      "id": 15,
      "name": "أشعة سينية للعنق",
      "basePrice": 130
    },
    {
      "id": 16,
      "name": "أشعة سينية للفقرات العنقية",
      "basePrice": 140
    },
    {
      "id": 17,
      "name": "أشعة سينية للفقرات الصدرية",
      "basePrice": 140
    },
    {
      "id": 18,
      "name": "أشعة سينية للفقرات القطنية",
      "basePrice": 140
    },
    {
      "id": 19,
      "name": "أشعة سينية للفقرات العجزية",
      "basePrice": 140
    },
    {
      "id": 20,
      "name": "أشعة سينية للفقرات العصعصية",
      "basePrice": 140
    },
    {
      "id": 21,
      "name": "أشعة مقطعية للصدر",
      "basePrice": 300
    },
    {
      "id": 22,
      "name": "أشعة مقطعية للبطن",
      "basePrice": 320
    },
    {
      "id": 23,
      "name": "أشعة مقطعية للحوض",
      "basePrice": 330
    },
    {
      "id": 24,
      "name": "أشعة مقطعية للعمود الفقري",
      "basePrice": 350
    },
    {
      "id": 25,
      "name": "أشعة مقطعية للرأس",
      "basePrice": 300
    },
    {
      "id": 26,
      "name": "أشعة مقطعية للذراع",
      "basePrice": 290
    },
    {
      "id": 27,
      "name": "أشعة مقطعية للساق",
      "basePrice": 290
    },
    {
      "id": 28,
      "name": "أشعة مقطعية للقدم",
      "basePrice": 290
    },
    {
      "id": 29,
      "name": "أشعة مقطعية لليد",
      "basePrice": 290
    },
    {
      "id": 30,
      "name": "أشعة مقطعية للكتف",
      "basePrice": 300
    },
    {
      "id": 31,
      "name": "أشعة مقطعية للركبة",
      "basePrice": 300
    },
    {
      "id": 32,
      "name": "أشعة مقطعية للكاحل",
      "basePrice": 300
    },
    {
      "id": 33,
      "name": "أشعة مقطعية للفخذ",
      "basePrice": 320
    },
    {
      "id": 34,
      "name": "أشعة مقطعية للرسغ",
      "basePrice": 300
    },
    {
      "id": 35,
      "name": "أشعة مقطعية للعنق",
      "basePrice": 320
    },
    {
      "id": 36,
      "name": "أشعة مقطعية للفقرات العنقية",
      "basePrice": 340
    },
    {
      "id": 37,
      "name": "أشعة مقطعية للفقرات الصدرية",
      "basePrice": 340
    },
    {
      "id": 38,
      "name": "أشعة مقطعية للفقرات القطنية",
      "basePrice": 340
    },
    {
      "id": 39,
      "name": "أشعة مقطعية للفقرات العجزية",
      "basePrice": 340
    },
    {
      "id": 40,
      "name": "أشعة مقطعية للفقرات العصعصية",
      "basePrice": 340
    },
    {
      "id": 41,
      "name": "أشعة رنين مغناطيسي للدماغ",
      "basePrice": 600
    },
    {
      "id": 42,
      "name": "أشعة رنين مغناطيسي للعمود الفقري",
      "basePrice": 650
    },
    {
      "id": 43,
      "name": "أشعة رنين مغناطيسي للبطن",
      "basePrice": 620
    },
    {
      "id": 44,
      "name": "أشعة رنين مغناطيسي للحوض",
      "basePrice": 630
    },
    {
      "id": 45,
      "name": "أشعة رنين مغناطيسي للركبة",
      "basePrice": 640
    },
    {
      "id": 46,
      "name": "أشعة رنين مغناطيسي للكتف",
      "basePrice": 640
    },
    {
      "id": 47,
      "name": "أشعة رنين مغناطيسي للعنق",
      "basePrice": 650
    },
    {
      "id": 48,
      "name": "أشعة رنين مغناطيسي للصدر",
      "basePrice": 650
    },
    {
      "id": 49,
      "name": "أشعة رنين مغناطيسي للرأس",
      "basePrice": 650
    },
    {
      "id": 50,
      "name": "أشعة رنين مغناطيسي للحوض",
      "basePrice": 650
    }
  ],
  "orders": [
    {
      "id": "a435",
      "patientId": "d080",
      "providerType": "doctor",
      "specialty": "طوارئ",
      "serviceName": "كشف طوارئ منزلي",
      "location": {
        "address": "",
        "lat": 30.134099748275556,
        "lng": 31.314086815372214
      },
      "basePrice": 350,
      "suggestedPrice": "300",
      "status": "rejected",
      "createdAt": "2025-07-15T09:04:14.002Z"
    },
    {
      "id": "6725",
      "patientId": "d080",
      "providerType": "doctor",
      "specialty": "طوارئ",
      "serviceName": "كشف طوارئ منزلي",
      "location": {
        "address": "",
        "lat": 30.134099748275556,
        "lng": 31.314086815372214
      },
      "basePrice": 350,
      "suggestedPrice": "300",
      "status": "rejected",
      "createdAt": "2025-07-15T09:04:16.575Z"
    },
    {
      "id": "605a",
      "patientId": "d080",
      "providerType": "nurse",
      "specialty": "",
      "serviceName": "حقن وريدي",
      "location": {
        "address": "عين شمس",
        "lat": 30.133779056013886,
        "lng": 31.314444271674674
      },
      "basePrice": 80,
      "suggestedPrice": "50",
      "status": "rejected",
      "createdAt": "2025-07-15T22:24:51.247Z"
    },
    {
      "id": "aa00",
      "patientId": "d080",
      "providerType": "nurse",
      "specialty": "",
      "serviceName": "حقن وريدي",
      "location": {
        "address": "عين شمس",
        "lat": 30.133779056013886,
        "lng": 31.314444271674674
      },
      "basePrice": 80,
      "suggestedPrice": "50",
      "status": "rejected",
      "createdAt": "2025-07-15T22:24:52.889Z"
    },
    {
      "id": "1842",
      "patientId": "d080",
      "providerType": "nurse",
      "specialty": "",
      "serviceNames": [
        "قياس ضغط الدم",
        "قياس السكر في الدم"
      ],
      "location": {
        "address": "",
        "lat": 30.133702917985367,
        "lng": 31.31441381625366
      },
      "basePrice": 110,
      "suggestedPrice": "100",
      "status": "accepted",
      "createdAt": "2025-07-15T22:44:58.699Z"
    },
    {
      "id": "390a",
      "patientId": "d080",
      "providerType": "physio",
      "specialty": "",
      "serviceNames": [
        "جلسة علاج طبيعي منزلي"
      ],
      "location": {
        "address": "",
        "lat": "",
        "lng": ""
      },
      "basePrice": 200,
      "suggestedPrice": "",
      "status": "rejected",
      "createdAt": "2025-07-15T22:48:38.969Z"
    },
    {
      "id": "057b",
      "patientId": "d080",
      "providerType": "nurse",
      "specialty": "",
      "serviceNames": [
        "قياس ضغط الدم",
        "قياس السكر في الدم"
      ],
      "location": {
        "address": "",
        "lat": "",
        "lng": ""
      },
      "basePrice": 110,
      "suggestedPrice": "150",
      "status": "new",
      "createdAt": "2025-07-15T22:57:48.597Z",
      "providerId": "d811",
      "providerName": "Christina Bolis Rezkallh Bolis",
      "providerPhone": "9282094830",
      "patientName": "ماريو فلتس شوقي",
      "address": ""
    },
    {
      "id": "e6d2",
      "patientId": "d080",
      "providerType": "nurse",
      "specialty": "",
      "serviceNames": [
        "قياس السكر في الدم",
        "حقن عضلي"
      ],
      "location": {
        "address": "79, شارع الاربعين, عرب الطويلة, شبرا الخيمة, القليوبية, 11832, مصر",
        "lat": 30.1337658822929,
        "lng": 31.314434863382406
      },
      "basePrice": 130,
      "suggestedPrice": "100",
      "status": "new",
      "createdAt": "2025-07-15T23:16:27.794Z",
      "providerId": "d811",
      "providerName": "Christina Bolis Rezkallh Bolis",
      "providerPhone": "9282094830",
      "patientName": "ماريو فلتس شوقي",
      "address": "79, شارع الاربعين, عرب الطويلة, شبرا الخيمة, القليوبية, 11832, مصر"
    },
    {
      "id": "4f6c",
      "patientId": "d080",
      "providerType": "nurse",
      "specialty": "",
      "serviceNames": [
        "قياس ضغط الدم",
        "قياس السكر في الدم"
      ],
      "location": {
        "address": "79, شارع الاربعين, عرب الطويلة, شبرا الخيمة, القليوبية, 11832, مصر",
        "lat": 30.133775030945785,
        "lng": 31.314443901236363
      },
      "basePrice": 110,
      "suggestedPrice": "1560",
      "status": "new",
      "createdAt": "2025-07-15T23:30:36.627Z",
      "providerId": "d811",
      "providerName": "Christina Bolis Rezkallh Bolis",
      "providerPhone": "9282094830",
      "patientName": "ماريو فلتس شوقي",
      "address": "79, شارع الاربعين, عرب الطويلة, شبرا الخيمة, القليوبية, 11832, مصر"
    }
  ],
  "services": [
    {
      "id": 1,
      "providerType": "doctor",
      "specialty": "طوارئ",
      "name": "كشف طوارئ منزلي",
      "basePrice": 350
    }
  ],
  "notifications": [
    {
      "id": "n001",
      "title": "تنبيه هام",
      "body": "يرجى مراجعة بياناتك الطبية.",
      "targetType": "patient",
      "targetId": "d080",
      "active": true,
      "showAsPopup": true,
      "createdAt": "2025-07-16T10:00:00.000Z"
    },
    {
      "id": "n002",
      "title": "إشعار جديد",
      "body": "تم إضافة خدمة جديدة.",
      "targetType": "provider",
      "targetId": "d811",
      "active": true,
      "showAsPopup": true,
      "createdAt": "2025-07-16T10:05:00.000Z"
    }
  ]
}